retk/.env.local
retk/__init__.py
retk/_version.py
retk/application.py
retk/config.py
retk/logger.py
retk/regex.py
retk/run.py
retk/safety.py
retk/const/__init__.py
retk/const/app.py
retk/const/languages.py
retk/const/new_user_default.py
retk/const/node_display.py
retk/const/node_types.py
retk/const/notice.py
retk/const/response_codes.py
retk/const/settings.py
retk/const/user_behavior_types.py
retk/const/user_sources.py
retk/const/user_types.py
retk/controllers/__init__.py
retk/controllers/account.py
retk/controllers/browser_extension.py
retk/controllers/manager.py
retk/controllers/notice.py
retk/controllers/oauth.py
retk/controllers/plugin.py
retk/controllers/recent.py
retk/controllers/statistic.py
retk/controllers/user.py
retk/controllers/utils.py
retk/controllers/ai/__init__.py
retk/controllers/ai/knowledge.py
retk/controllers/ai/llm_settings.py
retk/controllers/files/__init__.py
retk/controllers/files/upload_files.py
retk/controllers/node/__init__.py
retk/controllers/node/node_ops.py
retk/controllers/node/search.py
retk/controllers/node/trash_ops.py
retk/controllers/schemas/__init__.py
retk/controllers/schemas/account.py
retk/controllers/schemas/ai.py
retk/controllers/schemas/app_system.py
retk/controllers/schemas/browser_extension.py
retk/controllers/schemas/files.py
retk/controllers/schemas/manager.py
retk/controllers/schemas/node.py
retk/controllers/schemas/notice.py
retk/controllers/schemas/oauth.py
retk/controllers/schemas/plugin.py
retk/controllers/schemas/recent.py
retk/controllers/schemas/statistic.py
retk/controllers/schemas/user.py
retk/core/__init__.py
retk/core/analysis.py
retk/core/browser_extension.py
retk/core/notice.py
retk/core/recent.py
retk/core/self_hosted.py
retk/core/statistic.py
retk/core/user.py
retk/core/account/__init__.py
retk/core/account/app_captcha.py
retk/core/account/email.py
retk/core/account/manager.py
retk/core/ai/__init__.py
retk/core/ai/llm/__init__.py
retk/core/ai/llm/utils.py
retk/core/ai/llm/api/__init__.py
retk-0.3.1.dist-info/LICENSE
retk-0.3.1.dist-info/METADATA
retk-0.3.1.dist-info/WHEEL
retk-0.3.1.dist-info/top_level.txt
retk-0.3.1.dist-info/RECORD
